Metadata-Version: 2.1
Name: offline-judge
Version: 1.0.3
Summary: An offline equivalent of an online judge.
Home-page: https://github.com/Ninjaclasher/offline_judge
Author: Evan Zhang, jw4js
License: UNKNOWN
Platform: UNKNOWN
Classifier: Development Status :: 5 - Production/Stable
Classifier: Environment :: Console
Classifier: Intended Audience :: Developers
Classifier: License :: OSI Approved :: GNU General Public License v3 (GPLv3)
Classifier: Operating System :: POSIX :: Linux
Classifier: Programming Language :: Python
Classifier: Programming Language :: Python :: 3.7
